pydantic_settings_yaml/__init__.py
pydantic_settings_yaml/base_settings.py
tests/__init__.py
tests/test_base_settings.py
tests/data/config.yaml
tests/data/database_password
tests/data/database_username
pydantic_settings_yaml-0.2.0.dist-info/LICENSE
pydantic_settings_yaml-0.2.0.dist-info/METADATA
pydantic_settings_yaml-0.2.0.dist-info/WHEEL
pydantic_settings_yaml-0.2.0.dist-info/top_level.txt
pydantic_settings_yaml-0.2.0.dist-info/RECORD
