Metadata-Version: 2.1
Name: pydantic-settings-yaml
Version: 0.2.0
Summary: Yaml support for Pydantic settings
Classifier: Programming Language :: Python :: 3
Requires-Python: >=3.8
License-File: LICENSE
Requires-Dist: pyYAML
Requires-Dist: pydantic-settings (<3.0,>=2.0)
